{
   "formTitle": "smsNotify",
   "formName": "smsNotification",
   "actionPath": "https://dev.similac.com/api/public/update-profile",
   "redirectOnSuccessURL": "/content/an/similac/us/en/app/account/offers.html",
   "fields": [
      {
         "type": "htmltag"
      },
      {
         "label": "Never miss a deal",
         "type": "htmltag",
         "maxLength": 50
      },     
      {
      	 "label": "Phone Number",
         "name": "phone",
         "type": "tel",
         "validations": [
            {
               "errorType": "required",
               "errorMessage": "This is required field."
            },
            {
               "errorType": "phoneNumberUS",
               "errorMessage": "Phone Number format is (000) 000-0000."
            }
         ]
      },
      {
         "label": "TEXT ME ALERTS",
         "name": "submit",
         "type": "submit",
         "btnClassName": "btn btn-primary col-lg-3 col-md-6 col-sm-12 mt-4"
      }
   ]
}