{
  "_wizard": {
    "selector": ".o-wizard, .a-wizard",
    "title": "Wizard",
    "groups": {
      "steps": {
        "default-state": [
          {
            "label": "Step Text Size",
            "type": "unit",
            "config": {
              "default": {
                "key": "--wizard-step-label-font-size",
                "value": ""
              }
            }
          },
          {
            "label": "Step Margin",
            "type": "TRBL",
            "config": {
              "default": {
                "key": "--wizard-steps-margin",
                "value": ""
              }
            }
          },
          {
            "label": "Separator Color",
            "type": "color",
            "config": {
              "default": {
                "key": "--wizard-steps-sep-color",
                "value": "--gray-color"
              }
            }
          },
          {
            "label": "Icon Margin",
            "type": "TRBL",
            "config": {
              "default": {
                "key": "--wizard-step-icon-margin",
                "value": ""
              }
            }
          },
          {
            "label": "Icon Text Size",
            "type": "unit",
            "config": {
              "default": {
                "key": "--wizard-step-icon-font-size",
                "value": ""
              }
            }
          },
          {
            "label": "Icon Line Height",
            "type": "unit",
            "config": {
              "default": {
                "key": "--wizard-step-icon-line-height",
                "value": ""
              }
            }
          },

          {
            "label": "Icon Color",
            "type": "color",
            "config": {
              "default": {
                "key": "--wizard-steps-inactive-color",
                "value": "--gray-color"
              }
            }
          }
        ],
        "active": [
          {
            "label": "Icon Color",
            "type": "color",
            "config": {
              "default": {
                "key": "--wizard-step-active-color",
                "value": "--primary-color"
              }
            }
          }
        ],
        "completed": [
          {
            "label": "Icon Color",
            "type": "color",
            "config": {
              "default": {
                "key": "--wizard-step-complete-color",
                "value": "--primary-color"
              }
            }
          },
          {
            "label": "Icon Background Color",
            "type": "color",
            "config": {
              "default": {
                "key": "--wizard-step-icon-complete-bg-color",
                "value": "--white-color"
              }
            }
          }
        ]
      }
    }
  }
}
